pylorauna/__init__.py
pylorauna/lorauna.py
pylorauna-0.1.0.dist-info/WHEEL
pylorauna-0.1.0.dist-info/METADATA
pylorauna-0.1.0.dist-info/RECORD
