Metadata-Version: 2.1
Name: pylorauna
Version: 0.1.0
Summary: API Wrapper for the Lorauna API. Lorauna refers to the 'Sauna Lorrainebad' in Bern, CH
Author: Elia Bieri
Author-email: contact@eliabieri.com
Requires-Python: >=3.10,<4.0
Classifier: Programming Language :: Python :: 3
Classifier: Programming Language :: Python :: 3.10
Requires-Dist: gql[all] (>=3.4.0,<4.0.0)
